{
	"identifier": "Level_4",
	"uniqueIdentifer": "441ca330-7820-11ed-ad82-03a8cf12fd67",
	"x": 0,
	"y": 256,
	"width": 1400,
	"height": 728,
	"bgColor": "#171C39",
	"neighbourLevels": [
		{
			"levelIid": "b3820e90-7820-11ed-8e3a-3b167ff34615",
			"dir": "n"
		},
		{
			"levelIid": "deb14c10-7820-11ed-8ef5-132a76ca4d65",
			"dir": "n"
		},
		{
			"levelIid": "f7062980-7820-11ed-8ef5-53f1e5422273",
			"dir": "n"
		},
		{
			"levelIid": "fb8008d0-7820-11ed-9e5b-495294c54c2c",
			"dir": "n"
		}
	],
	"customFields" : {},
	"layers": [
		"IntGrid.png"
	],
	"entities": {
		"Enemy": [
			{
				"id": "Enemy",
				"iid": "6a376660-7820-11ed-ad82-3f6aae37db2a",
				"layer": "Entities",
				"x": 968,
				"y": 320,
				"width": 8,
				"height": 8,
				"color": 16711748,
				"customFields" : {}
			},
			{
				"id": "Enemy",
				"iid": "6ac59ca0-7820-11ed-ad82-23356f5cea7f",
				"layer": "Entities",
				"x": 1008,
				"y": 320,
				"width": 8,
				"height": 8,
				"color": 16711748,
				"customFields" : {}
			},
			{
				"id": "Enemy",
				"iid": "0e589ca0-7820-11ed-ad82-f57b955ab90b",
				"layer": "Entities",
				"x": 640,
				"y": 160,
				"width": 8,
				"height": 8,
				"color": 16711748,
				"customFields" : {}
			},
			{
				"id": "Enemy",
				"iid": "0fa085f0-7820-11ed-ad82-85dcd850779e",
				"layer": "Entities",
				"x": 776,
				"y": 272,
				"width": 8,
				"height": 8,
				"color": 16711748,
				"customFields" : {}
			},
			{
				"id": "Enemy",
				"iid": "11165d10-7820-11ed-ad82-af197d9c00ce",
				"layer": "Entities",
				"x": 952,
				"y": 184,
				"width": 8,
				"height": 8,
				"color": 16711748,
				"customFields" : {}
			},
			{
				"id": "Enemy",
				"iid": "12bf5220-7820-11ed-ad82-25729a569bb5",
				"layer": "Entities",
				"x": 1184,
				"y": 224,
				"width": 8,
				"height": 8,
				"color": 16711748,
				"customFields" : {}
			},
			{
				"id": "Enemy",
				"iid": "14bbe570-7820-11ed-ad82-1d27385a88f8",
				"layer": "Entities",
				"x": 496,
				"y": 136,
				"width": 8,
				"height": 8,
				"color": 16711748,
				"customFields" : {}
			},
			{
				"id": "Enemy",
				"iid": "1593f5f0-7820-11ed-ad82-d1544d501861",
				"layer": "Entities",
				"x": 560,
				"y": 56,
				"width": 8,
				"height": 8,
				"color": 16711748,
				"customFields" : {}
			},
			{
				"id": "Enemy",
				"iid": "165a7a40-7820-11ed-ad82-f1ea7f6ff56b",
				"layer": "Entities",
				"x": 240,
				"y": 152,
				"width": 8,
				"height": 8,
				"color": 16711748,
				"customFields" : {}
			},
			{
				"id": "Enemy",
				"iid": "16eb6fa0-7820-11ed-ad82-a7c510029a35",
				"layer": "Entities",
				"x": 128,
				"y": 96,
				"width": 8,
				"height": 8,
				"color": 16711748,
				"customFields" : {}
			},
			{
				"id": "Enemy",
				"iid": "1872fa00-7820-11ed-ad82-cf39e704bc94",
				"layer": "Entities",
				"x": 152,
				"y": 248,
				"width": 8,
				"height": 8,
				"color": 16711748,
				"customFields" : {}
			},
			{
				"id": "Enemy",
				"iid": "1d62b5a0-7820-11ed-ad82-01fb80ddea3e",
				"layer": "Entities",
				"x": 248,
				"y": 304,
				"width": 8,
				"height": 8,
				"color": 16711748,
				"customFields" : {}
			},
			{
				"id": "Enemy",
				"iid": "da946510-7820-11ed-ad82-45d72aaa8f1b",
				"layer": "Entities",
				"x": 160,
				"y": 472,
				"width": 8,
				"height": 8,
				"color": 16711748,
				"customFields" : {}
			},
			{
				"id": "Enemy",
				"iid": "dae82a60-7820-11ed-ad82-671092ba71f5",
				"layer": "Entities",
				"x": 280,
				"y": 472,
				"width": 8,
				"height": 8,
				"color": 16711748,
				"customFields" : {}
			},
			{
				"id": "Enemy",
				"iid": "db4146e0-7820-11ed-ad82-ad4e3eb79afa",
				"layer": "Entities",
				"x": 376,
				"y": 472,
				"width": 8,
				"height": 8,
				"color": 16711748,
				"customFields" : {}
			},
			{
				"id": "Enemy",
				"iid": "db953340-7820-11ed-ad82-87d02c1bc1f2",
				"layer": "Entities",
				"x": 328,
				"y": 520,
				"width": 8,
				"height": 8,
				"color": 16711748,
				"customFields" : {}
			},
			{
				"id": "Enemy",
				"iid": "dc053320-7820-11ed-ad82-bf2afc267ad2",
				"layer": "Entities",
				"x": 208,
				"y": 520,
				"width": 8,
				"height": 8,
				"color": 16711748,
				"customFields" : {}
			},
			{
				"id": "Enemy",
				"iid": "dc5e0180-7820-11ed-ad82-c1f5174dbcec",
				"layer": "Entities",
				"x": 96,
				"y": 520,
				"width": 8,
				"height": 8,
				"color": 16711748,
				"customFields" : {}
			},
			{
				"id": "Enemy",
				"iid": "dcb4ad00-7820-11ed-ad82-f9a588ded6e3",
				"layer": "Entities",
				"x": 136,
				"y": 568,
				"width": 8,
				"height": 8,
				"color": 16711748,
				"customFields" : {}
			},
			{
				"id": "Enemy",
				"iid": "dd6697e0-7820-11ed-ad82-ab1eb0a25f85",
				"layer": "Entities",
				"x": 296,
				"y": 560,
				"width": 8,
				"height": 8,
				"color": 16711748,
				"customFields" : {}
			},
			{
				"id": "Enemy",
				"iid": "ddb81340-7820-11ed-ad82-a3de93c1ca87",
				"layer": "Entities",
				"x": 392,
				"y": 560,
				"width": 8,
				"height": 8,
				"color": 16711748,
				"customFields" : {}
			},
			{
				"id": "Enemy",
				"iid": "de2cf520-7820-11ed-ad82-e1806ddf56ab",
				"layer": "Entities",
				"x": 336,
				"y": 608,
				"width": 8,
				"height": 8,
				"color": 16711748,
				"customFields" : {}
			},
			{
				"id": "Enemy",
				"iid": "de80e180-7820-11ed-ad82-09d78d3dd1bd",
				"layer": "Entities",
				"x": 224,
				"y": 616,
				"width": 8,
				"height": 8,
				"color": 16711748,
				"customFields" : {}
			},
			{
				"id": "Enemy",
				"iid": "dee19f20-7820-11ed-ad82-13f47fcbe7bc",
				"layer": "Entities",
				"x": 104,
				"y": 600,
				"width": 8,
				"height": 8,
				"color": 16711748,
				"customFields" : {}
			},
			{
				"id": "Enemy",
				"iid": "dfef3e90-7820-11ed-ad82-6bc143093b44",
				"layer": "Entities",
				"x": 96,
				"y": 696,
				"width": 8,
				"height": 8,
				"color": 16711748,
				"customFields" : {}
			},
			{
				"id": "Enemy",
				"iid": "e0998850-7820-11ed-ad82-931ac85cebfe",
				"layer": "Entities",
				"x": 192,
				"y": 696,
				"width": 8,
				"height": 8,
				"color": 16711748,
				"customFields" : {}
			},
			{
				"id": "Enemy",
				"iid": "e0de3270-7820-11ed-ad82-4579cea2c66d",
				"layer": "Entities",
				"x": 272,
				"y": 696,
				"width": 8,
				"height": 8,
				"color": 16711748,
				"customFields" : {}
			},
			{
				"id": "Enemy",
				"iid": "e24c8f80-7820-11ed-ad82-f9d6d76930da",
				"layer": "Entities",
				"x": 312,
				"y": 696,
				"width": 8,
				"height": 8,
				"color": 16711748,
				"customFields" : {}
			},
			{
				"id": "Enemy",
				"iid": "e467ce60-7820-11ed-ad82-9dd239c5f3a0",
				"layer": "Entities",
				"x": 560,
				"y": 568,
				"width": 8,
				"height": 8,
				"color": 16711748,
				"customFields" : {}
			},
			{
				"id": "Enemy",
				"iid": "e5266370-7820-11ed-ad82-6dbf1eb71fb7",
				"layer": "Entities",
				"x": 736,
				"y": 552,
				"width": 8,
				"height": 8,
				"color": 16711748,
				"customFields" : {}
			},
			{
				"id": "Enemy",
				"iid": "e5e2ae90-7820-11ed-ad82-2161e4ecd139",
				"layer": "Entities",
				"x": 688,
				"y": 472,
				"width": 8,
				"height": 8,
				"color": 16711748,
				"customFields" : {}
			},
			{
				"id": "Enemy",
				"iid": "e87a7070-7820-11ed-ad82-17b991a5c37a",
				"layer": "Entities",
				"x": 592,
				"y": 448,
				"width": 8,
				"height": 8,
				"color": 16711748,
				"customFields" : {}
			},
			{
				"id": "Enemy",
				"iid": "ebfc4430-7820-11ed-ad82-e16e37fa3879",
				"layer": "Entities",
				"x": 920,
				"y": 536,
				"width": 8,
				"height": 8,
				"color": 16711748,
				"customFields" : {}
			},
			{
				"id": "Enemy",
				"iid": "ee63a740-7820-11ed-ad82-3dda5c8dc1be",
				"layer": "Entities",
				"x": 1048,
				"y": 600,
				"width": 8,
				"height": 8,
				"color": 16711748,
				"customFields" : {}
			},
			{
				"id": "Enemy",
				"iid": "eefc3dc0-7820-11ed-ad82-a914e6e2e2c6",
				"layer": "Entities",
				"x": 1032,
				"y": 456,
				"width": 8,
				"height": 8,
				"color": 16711748,
				"customFields" : {}
			},
			{
				"id": "Enemy",
				"iid": "efe62890-7820-11ed-ad82-87d973bbe524",
				"layer": "Entities",
				"x": 1200,
				"y": 616,
				"width": 8,
				"height": 8,
				"color": 16711748,
				"customFields" : {}
			},
			{
				"id": "Enemy",
				"iid": "f0c60140-7820-11ed-ad82-e30c5fc8b72a",
				"layer": "Entities",
				"x": 1304,
				"y": 536,
				"width": 8,
				"height": 8,
				"color": 16711748,
				"customFields" : {}
			},
			{
				"id": "Enemy",
				"iid": "f1a84af0-7820-11ed-ad82-7dbaa488993a",
				"layer": "Entities",
				"x": 1144,
				"y": 472,
				"width": 8,
				"height": 8,
				"color": 16711748,
				"customFields" : {}
			}
		],
		"Power": [
			{
				"id": "Power",
				"iid": "98fb2a40-7820-11ed-88a8-b30dac8b0450",
				"layer": "Entities",
				"x": 696,
				"y": 232,
				"width": 16,
				"height": 16,
				"color": 16705377,
				"customFields" : {}
			},
			{
				"id": "Power",
				"iid": "9a7fa760-7820-11ed-88a8-0f00887da4e3",
				"layer": "Entities",
				"x": 1288,
				"y": 248,
				"width": 16,
				"height": 16,
				"color": 16705377,
				"customFields" : {}
			},
			{
				"id": "Power",
				"iid": "9d28f570-7820-11ed-88a8-5959cf417f1f",
				"layer": "Entities",
				"x": 1280,
				"y": 408,
				"width": 16,
				"height": 16,
				"color": 16705377,
				"customFields" : {}
			},
			{
				"id": "Power",
				"iid": "9f075260-7820-11ed-88a8-fd7d3d7846f7",
				"layer": "Entities",
				"x": 624,
				"y": 528,
				"width": 16,
				"height": 16,
				"color": 16705377,
				"customFields" : {}
			},
			{
				"id": "Power",
				"iid": "a2b7d740-7820-11ed-88a8-7948ccf01fb6",
				"layer": "Entities",
				"x": 240,
				"y": 216,
				"width": 16,
				"height": 16,
				"color": 16705377,
				"customFields" : {}
			}
		],
		"Player": [
			{
				"id": "Player",
				"iid": "88f6ae10-7820-11ed-b9da-ddf95f64f706",
				"layer": "Entities",
				"x": 16,
				"y": 88,
				"width": 8,
				"height": 8,
				"color": 39387,
				"customFields" : {}
			}
		]
	}
}